README.rst
setup.py
ClarityHealthCheck/__init__.py
ClarityHealthCheck/apps.py
ClarityHealthCheck/hc_classes.py
ClarityHealthCheck/hc_utils.py
ClarityHealthCheck/logger.py
ClarityHealthCheck/settings.py
ClarityHealthCheck/urls.py
ClarityHealthCheck/views.py
ClarityHealthCheck/wsgi.py
ClarityHealthCheck.egg-info/PKG-INFO
ClarityHealthCheck.egg-info/SOURCES.txt
ClarityHealthCheck.egg-info/dependency_links.txt
ClarityHealthCheck.egg-info/requires.txt
ClarityHealthCheck.egg-info/top_level.txt